genetic_algorithm_nas/__init__.py
genetic_algorithm_nas/crossover.py
genetic_algorithm_nas/errors.py
genetic_algorithm_nas/fitness_function.py
genetic_algorithm_nas/genetic_algorithm_nas.py
genetic_algorithm_nas/initial_population_generator.py
genetic_algorithm_nas/metrics.py
genetic_algorithm_nas/mutation.py
genetic_algorithm_nas/next_population_generator.py
genetic_algorithm_nas/organism.py
genetic_algorithm_nas/preprocessing.py
genetic_algorithm_nas-0.1.9.dist-info/LICENSE
genetic_algorithm_nas-0.1.9.dist-info/METADATA
genetic_algorithm_nas-0.1.9.dist-info/WHEEL
genetic_algorithm_nas-0.1.9.dist-info/top_level.txt
genetic_algorithm_nas-0.1.9.dist-info/RECORD
