Metadata-Version: 2.1
Name: genetic-algorithm-nas
Version: 0.1.9
Summary: Feature Selection using Genetic Algorithm (DEAP Framework)
Home-page: https://featureselectionga.readthedocs.io
Author: shilash
Author-email: kaushalshetty@outlook.com
License: MIT
Project-URL: Source, https://github.com/kaushalshetty/FeatureSelectionGA
Project-URL: Documentation, https://featureselectionga.readthedocs.io
Project-URL: Changelog, https://featureselectionga.readthedocs.io/en/latest/changelog.html
Keywords: feature selection,Genetic Algorithm,DEAP
Classifier: Development Status :: 2 - Pre-Alpha
Classifier: Intended Audience :: Developers
Classifier: License :: OSI Approved :: MIT License
Classifier: Natural Language :: English
Classifier: Programming Language :: Python :: 3
Classifier: Programming Language :: Python :: 3.6
Classifier: Programming Language :: Python :: 3.7
Classifier: Programming Language :: Python :: 3.8
Requires-Python: >=3.6
License-File: LICENSE
